mlpro_int_pettingzoo/__init__.py
mlpro_int_pettingzoo/wrappers/__init__.py
mlpro_int_pettingzoo/wrappers/basics.py
mlpro_int_pettingzoo-1.0.2.dist-info/licenses/LICENSE
mlpro_int_pettingzoo-1.0.2.dist-info/METADATA
mlpro_int_pettingzoo-1.0.2.dist-info/WHEEL
mlpro_int_pettingzoo-1.0.2.dist-info/top_level.txt
mlpro_int_pettingzoo-1.0.2.dist-info/RECORD
